{
  "reference": "Job 35",
  "verses": [
    {
      "book_id": "JOB",
      "book_name": "Job",
      "chapter": 35,
      "verse": 1,
      "text": "Moreover Elihu answered,\n"
    },
    {
      "book_id": "JOB",
      "book_name": "Job",
      "chapter": 35,
      "verse": 2,
      "text": "“Do you think this to be your right,\nor do you say, ‘My righteousness is more than God’s,’\n"
    },
    {
      "book_id": "JOB",
      "book_name": "Job",
      "chapter": 35,
      "verse": 3,
      "text": "That you ask, ‘What advantage will it be to you?\nWhat profit shall I have, more than if I had sinned?’\n"
    },
    {
      "book_id": "JOB",
      "book_name": "Job",
      "chapter": 35,
      "verse": 4,
      "text": "I will answer you,\nand your companions with you.\n"
    },
    {
      "book_id": "JOB",
      "book_name": "Job",
      "chapter": 35,
      "verse": 5,
      "text": "Look to the heavens, and see.\nSee the skies, which are higher than you.\n"
    },
    {
      "book_id": "JOB",
      "book_name": "Job",
      "chapter": 35,
      "verse": 6,
      "text": "If you have sinned, what effect do you have against him?\nIf your transgressions are multiplied, what do you do to him?\n"
    },
    {
      "book_id": "JOB",
      "book_name": "Job",
      "chapter": 35,
      "verse": 7,
      "text": "If you are righteous, what do you give him?\nOr what does he receive from your hand?\n"
    },
    {
      "book_id": "JOB",
      "book_name": "Job",
      "chapter": 35,
      "verse": 8,
      "text": "Your wickedness may hurt a man as you are,\nand your righteousness may profit a son of man.\n"
    },
    {
      "book_id": "JOB",
      "book_name": "Job",
      "chapter": 35,
      "verse": 9,
      "text": "“By reason of the multitude of oppressions they cry out.\nThey cry for help by reason of the arm of the mighty.\n"
    },
    {
      "book_id": "JOB",
      "book_name": "Job",
      "chapter": 35,
      "verse": 10,
      "text": "But no one says, ‘Where is God my Maker,\nwho gives songs in the night,\n"
    },
    {
      "book_id": "JOB",
      "book_name": "Job",
      "chapter": 35,
      "verse": 11,
      "text": "who teaches us more than the animals of the earth,\nand makes us wiser than the birds of the sky?’\n"
    },
    {
      "book_id": "JOB",
      "book_name": "Job",
      "chapter": 35,
      "verse": 12,
      "text": "There they cry, but no one gives answer,\nbecause of the pride of evil men.\n"
    },
    {
      "book_id": "JOB",
      "book_name": "Job",
      "chapter": 35,
      "verse": 13,
      "text": "Surely God will not hear an empty cry,\nneither will the Almighty regard it.\n"
    },
    {
      "book_id": "JOB",
      "book_name": "Job",
      "chapter": 35,
      "verse": 14,
      "text": "How much less when you say you don’t see him.\nThe cause is before him, and you wait for him!\n"
    },
    {
      "book_id": "JOB",
      "book_name": "Job",
      "chapter": 35,
      "verse": 15,
      "text": "But now, because he has not visited in his anger,\nneither does he greatly regard arrogance.\n"
    },
    {
      "book_id": "JOB",
      "book_name": "Job",
      "chapter": 35,
      "verse": 16,
      "text": "Therefore Job opens his mouth with empty talk,\nand he multiplies words without knowledge.”\n"
    }
  ],
  "text": "Moreover Elihu answered,\n“Do you think this to be your right,\nor do you say, ‘My righteousness is more than God’s,’\nThat you ask, ‘What advantage will it be to you?\nWhat profit shall I have, more than if I had sinned?’\nI will answer you,\nand your companions with you.\nLook to the heavens, and see.\nSee the skies, which are higher than you.\nIf you have sinned, what effect do you have against him?\nIf your transgressions are multiplied, what do you do to him?\nIf you are righteous, what do you give him?\nOr what does he receive from your hand?\nYour wickedness may hurt a man as you are,\nand your righteousness may profit a son of man.\n“By reason of the multitude of oppressions they cry out.\nThey cry for help by reason of the arm of the mighty.\nBut no one says, ‘Where is God my Maker,\nwho gives songs in the night,\nwho teaches us more than the animals of the earth,\nand makes us wiser than the birds of the sky?’\nThere they cry, but no one gives answer,\nbecause of the pride of evil men.\nSurely God will not hear an empty cry,\nneither will the Almighty regard it.\nHow much less when you say you don’t see him.\nThe cause is before him, and you wait for him!\nBut now, because he has not visited in his anger,\nneither does he greatly regard arrogance.\nTherefore Job opens his mouth with empty talk,\nand he multiplies words without knowledge.”\n",
  "translation_id": "web",
  "translation_name": "World English Bible",
  "translation_note": "Public Domain"
}