{
  "reference": "Matthew 5",
  "verses": [
    {
      "book_id": "MAT",
      "book_name": "Matthew",
      "chapter": 5,
      "verse": 1,
      "text": "Seeing the multitudes, he went up onto the mountain. When he had sat down, his disciples came to him.\n"
    },
    {
      "book_id": "MAT",
      "book_name": "Matthew",
      "chapter": 5,
      "verse": 2,
      "text": "He opened his mouth and taught them, saying,\n"
    },
    {
      "book_id": "MAT",
      "book_name": "Matthew",
      "chapter": 5,
      "verse": 3,
      "text": "\n“Blessed are the poor in spirit,\nfor theirs is the Kingdom of Heaven.\n"
    },
    {
      "book_id": "MAT",
      "book_name": "Matthew",
      "chapter": 5,
      "verse": 4,
      "text": "\nBlessed are those who mourn,\nfor they shall be comforted.\n"
    },
    {
      "book_id": "MAT",
      "book_name": "Matthew",
      "chapter": 5,
      "verse": 5,
      "text": "\nBlessed are the gentle,\nfor they shall inherit the earth.\n"
    },
    {
      "book_id": "MAT",
      "book_name": "Matthew",
      "chapter": 5,
      "verse": 6,
      "text": "\nBlessed are those who hunger and thirst after righteousness,\n\nfor they shall be filled.\n"
    },
    {
      "book_id": "MAT",
      "book_name": "Matthew",
      "chapter": 5,
      "verse": 7,
      "text": "\nBlessed are the merciful,\nfor they shall obtain mercy.\n"
    },
    {
      "book_id": "MAT",
      "book_name": "Matthew",
      "chapter": 5,
      "verse": 8,
      "text": "\nBlessed are the pure in heart,\nfor they shall see God.\n"
    },
    {
      "book_id": "MAT",
      "book_name": "Matthew",
      "chapter": 5,
      "verse": 9,
      "text": "\nBlessed are the peacemakers,\nfor they shall be called children of God.\n"
    },
    {
      "book_id": "MAT",
      "book_name": "Matthew",
      "chapter": 5,
      "verse": 10,
      "text": "\nBlessed are those who have been persecuted for righteousness’ sake,\n\nfor theirs is the Kingdom of Heaven.\n"
    },
    {
      "book_id": "MAT",
      "book_name": "Matthew",
      "chapter": 5,
      "verse": 11,
      "text": "\n“Blessed are you when people reproach you, persecute you, and say all kinds of evil against you falsely, for my sake.\n\n"
    },
    {
      "book_id": "MAT",
      "book_name": "Matthew",
      "chapter": 5,
      "verse": 12,
      "text": "\nRejoice, and be exceedingly glad, for great is your reward in heaven. For that is how they persecuted the prophets who were before you.\n\n"
    },
    {
      "book_id": "MAT",
      "book_name": "Matthew",
      "chapter": 5,
      "verse": 13,
      "text": "\n“You are the salt of the earth, but if the salt has lost its flavor, with what will it be salted? It is then good for nothing, but to be cast out and trodden under the feet of men.\n\n"
    },
    {
      "book_id": "MAT",
      "book_name": "Matthew",
      "chapter": 5,
      "verse": 14,
      "text": "\nYou are the light of the world. A city located on a hill can’t be hidden.\n\n"
    },
    {
      "book_id": "MAT",
      "book_name": "Matthew",
      "chapter": 5,
      "verse": 15,
      "text": "\nNeither do you light a lamp, and put it under a measuring basket, but on a stand; and it shines to all who are in the house.\n\n"
    },
    {
      "book_id": "MAT",
      "book_name": "Matthew",
      "chapter": 5,
      "verse": 16,
      "text": "\nEven so, let your light shine before men; that they may see your good works, and glorify your Father who is in heaven.\n"
    },
    {
      "book_id": "MAT",
      "book_name": "Matthew",
      "chapter": 5,
      "verse": 17,
      "text": "\n“Don’t think that I came to destroy the law or the prophets. I didn’t come to destroy, but to fulfill.\n\n"
    },
    {
      "book_id": "MAT",
      "book_name": "Matthew",
      "chapter": 5,
      "verse": 18,
      "text": "\nFor most certainly, I tell you, until heaven and earth pass away, not even one smallest letter\nor one tiny pen stroke\nshall in any way pass away from the law, until all things are accomplished.\n\n"
    },
    {
      "book_id": "MAT",
      "book_name": "Matthew",
      "chapter": 5,
      "verse": 19,
      "text": "\nWhoever, therefore, shall break one of these least commandments, and teach others to do so, shall be called least in the Kingdom of Heaven; but whoever shall do and teach them shall be called great in the Kingdom of Heaven.\n\n"
    },
    {
      "book_id": "MAT",
      "book_name": "Matthew",
      "chapter": 5,
      "verse": 20,
      "text": "\nFor I tell you that unless your righteousness exceeds that of the scribes and Pharisees, there is no way you will enter into the Kingdom of Heaven.\n"
    },
    {
      "book_id": "MAT",
      "book_name": "Matthew",
      "chapter": 5,
      "verse": 21,
      "text": "\n“You have heard that it was said to the ancient ones, ‘You shall not murder;’\nand ‘Whoever murders will be in danger of the judgment.’\n\n"
    },
    {
      "book_id": "MAT",
      "book_name": "Matthew",
      "chapter": 5,
      "verse": 22,
      "text": "\nBut I tell you, that everyone who is angry with his brother without a cause\n\n\nwill be in danger of the judgment; and whoever says to his brother, ‘Raca!’\n\nwill be in danger of the council; and whoever says, ‘You fool!’ will be in danger of the fire of Gehenna.\n\n"
    },
    {
      "book_id": "MAT",
      "book_name": "Matthew",
      "chapter": 5,
      "verse": 23,
      "text": "\n“If therefore you are offering your gift at the altar, and there remember that your brother has anything against you,\n\n"
    },
    {
      "book_id": "MAT",
      "book_name": "Matthew",
      "chapter": 5,
      "verse": 24,
      "text": "\nleave your gift there before the altar, and go your way. First be reconciled to your brother, and then come and offer your gift.\n\n"
    },
    {
      "book_id": "MAT",
      "book_name": "Matthew",
      "chapter": 5,
      "verse": 25,
      "text": "\nAgree with your adversary quickly, while you are with him on the way; lest perhaps the prosecutor deliver you to the judge, and the judge deliver you to the officer, and you be cast into prison.\n\n"
    },
    {
      "book_id": "MAT",
      "book_name": "Matthew",
      "chapter": 5,
      "verse": 26,
      "text": "\nMost certainly I tell you, you shall by no means get out of there, until you have paid the last penny.\n"
    },
    {
      "book_id": "MAT",
      "book_name": "Matthew",
      "chapter": 5,
      "verse": 27,
      "text": "\n“You have heard that it was said,\n\n‘You shall not commit adultery;’\n"
    },
    {
      "book_id": "MAT",
      "book_name": "Matthew",
      "chapter": 5,
      "verse": 28,
      "text": "\nbut I tell you that everyone who gazes at a woman to lust after her has committed adultery with her already in his heart.\n\n"
    },
    {
      "book_id": "MAT",
      "book_name": "Matthew",
      "chapter": 5,
      "verse": 29,
      "text": "\nIf your right eye causes you to stumble, pluck it out and throw it away from you. For it is more profitable for you that one of your members should perish, than for your whole body to be cast into Gehenna.\n"
    },
    {
      "book_id": "MAT",
      "book_name": "Matthew",
      "chapter": 5,
      "verse": 30,
      "text": "\nIf your right hand causes you to stumble, cut it off, and throw it away from you. For it is more profitable for you that one of your members should perish, than for your whole body to be cast into Gehenna.\n"
    },
    {
      "book_id": "MAT",
      "book_name": "Matthew",
      "chapter": 5,
      "verse": 31,
      "text": "\n“It was also said, ‘Whoever shall put away his wife, let him give her a writing of divorce,’\n"
    },
    {
      "book_id": "MAT",
      "book_name": "Matthew",
      "chapter": 5,
      "verse": 32,
      "text": "\nbut I tell you that whoever puts away his wife, except for the cause of sexual immorality, makes her an adulteress; and whoever marries her when she is put away commits adultery.\n"
    },
    {
      "book_id": "MAT",
      "book_name": "Matthew",
      "chapter": 5,
      "verse": 33,
      "text": "\n“Again you have heard that it was said to them of old time, ‘You shall not make false vows, but shall perform to the Lord your vows,’\n"
    },
    {
      "book_id": "MAT",
      "book_name": "Matthew",
      "chapter": 5,
      "verse": 34,
      "text": "\nbut I tell you, don’t swear at all: neither by heaven, for it is the throne of God;\n\n"
    },
    {
      "book_id": "MAT",
      "book_name": "Matthew",
      "chapter": 5,
      "verse": 35,
      "text": "\nnor by the earth, for it is the footstool of his feet; nor by Jerusalem, for it is the city of the great King.\n\n"
    },
    {
      "book_id": "MAT",
      "book_name": "Matthew",
      "chapter": 5,
      "verse": 36,
      "text": "\nNeither shall you swear by your head, for you can’t make one hair white or black.\n\n"
    },
    {
      "book_id": "MAT",
      "book_name": "Matthew",
      "chapter": 5,
      "verse": 37,
      "text": "\nBut let your ‘Yes’ be ‘Yes’ and your ‘No’ be ‘No.’ Whatever is more than these is of the evil one.\n"
    },
    {
      "book_id": "MAT",
      "book_name": "Matthew",
      "chapter": 5,
      "verse": 38,
      "text": "\n“You have heard that it was said, ‘An eye for an eye, and a tooth for a tooth.’\n"
    },
    {
      "book_id": "MAT",
      "book_name": "Matthew",
      "chapter": 5,
      "verse": 39,
      "text": "\nBut I tell you, don’t resist him who is evil; but whoever strikes you on your right cheek, turn to him the other also.\n\n"
    },
    {
      "book_id": "MAT",
      "book_name": "Matthew",
      "chapter": 5,
      "verse": 40,
      "text": "\nIf anyone sues you to take away your coat, let him have your cloak also.\n\n"
    },
    {
      "book_id": "MAT",
      "book_name": "Matthew",
      "chapter": 5,
      "verse": 41,
      "text": "\nWhoever compels you to go one mile, go with him two.\n\n"
    },
    {
      "book_id": "MAT",
      "book_name": "Matthew",
      "chapter": 5,
      "verse": 42,
      "text": "\nGive to him who asks you, and don’t turn away him who desires to borrow from you.\n"
    },
    {
      "book_id": "MAT",
      "book_name": "Matthew",
      "chapter": 5,
      "verse": 43,
      "text": "\n“You have heard that it was said, ‘You shall love your neighbor\n\nand hate your enemy.’\n"
    },
    {
      "book_id": "MAT",
      "book_name": "Matthew",
      "chapter": 5,
      "verse": 44,
      "text": "\nBut I tell you, love your enemies, bless those who curse you, do good to those who hate you, and pray for those who mistreat you and persecute you,\n\n"
    },
    {
      "book_id": "MAT",
      "book_name": "Matthew",
      "chapter": 5,
      "verse": 45,
      "text": "\nthat you may be children of your Father who is in heaven. For he makes his sun to rise on the evil and the good, and sends rain on the just and the unjust.\n\n"
    },
    {
      "book_id": "MAT",
      "book_name": "Matthew",
      "chapter": 5,
      "verse": 46,
      "text": "\nFor if you love those who love you, what reward do you have? Don’t even the tax collectors do the same?\n\n"
    },
    {
      "book_id": "MAT",
      "book_name": "Matthew",
      "chapter": 5,
      "verse": 47,
      "text": "\nIf you only greet your friends, what more do you do than others? Don’t even the tax collectors\ndo the same?\n\n"
    },
    {
      "book_id": "MAT",
      "book_name": "Matthew",
      "chapter": 5,
      "verse": 48,
      "text": "\nTherefore you shall be perfect, just as your Father in heaven is perfect.\n"
    }
  ],
  "text": "Seeing the multitudes, he went up onto the mountain. When he had sat down, his disciples came to him.\nHe opened his mouth and taught them, saying,\n\n“Blessed are the poor in spirit,\nfor theirs is the Kingdom of Heaven.\n\nBlessed are those who mourn,\nfor they shall be comforted.\n\nBlessed are the gentle,\nfor they shall inherit the earth.\n\nBlessed are those who hunger and thirst after righteousness,\n\nfor they shall be filled.\n\nBlessed are the merciful,\nfor they shall obtain mercy.\n\nBlessed are the pure in heart,\nfor they shall see God.\n\nBlessed are the peacemakers,\nfor they shall be called children of God.\n\nBlessed are those who have been persecuted for righteousness’ sake,\n\nfor theirs is the Kingdom of Heaven.\n\n“Blessed are you when people reproach you, persecute you, and say all kinds of evil against you falsely, for my sake.\n\n\nRejoice, and be exceedingly glad, for great is your reward in heaven. For that is how they persecuted the prophets who were before you.\n\n\n“You are the salt of the earth, but if the salt has lost its flavor, with what will it be salted? It is then good for nothing, but to be cast out and trodden under the feet of men.\n\n\nYou are the light of the world. A city located on a hill can’t be hidden.\n\n\nNeither do you light a lamp, and put it under a measuring basket, but on a stand; and it shines to all who are in the house.\n\n\nEven so, let your light shine before men; that they may see your good works, and glorify your Father who is in heaven.\n\n“Don’t think that I came to destroy the law or the prophets. I didn’t come to destroy, but to fulfill.\n\n\nFor most certainly, I tell you, until heaven and earth pass away, not even one smallest letter\nor one tiny pen stroke\nshall in any way pass away from the law, until all things are accomplished.\n\n\nWhoever, therefore, shall break one of these least commandments, and teach others to do so, shall be called least in the Kingdom of Heaven; but whoever shall do and teach them shall be called great in the Kingdom of Heaven.\n\n\nFor I tell you that unless your righteousness exceeds that of the scribes and Pharisees, there is no way you will enter into the Kingdom of Heaven.\n\n“You have heard that it was said to the ancient ones, ‘You shall not murder;’\nand ‘Whoever murders will be in danger of the judgment.’\n\n\nBut I tell you, that everyone who is angry with his brother without a cause\n\n\nwill be in danger of the judgment; and whoever says to his brother, ‘Raca!’\n\nwill be in danger of the council; and whoever says, ‘You fool!’ will be in danger of the fire of Gehenna.\n\n\n“If therefore you are offering your gift at the altar, and there remember that your brother has anything against you,\n\n\nleave your gift there before the altar, and go your way. First be reconciled to your brother, and then come and offer your gift.\n\n\nAgree with your adversary quickly, while you are with him on the way; lest perhaps the prosecutor deliver you to the judge, and the judge deliver you to the officer, and you be cast into prison.\n\n\nMost certainly I tell you, you shall by no means get out of there, until you have paid the last penny.\n\n“You have heard that it was said,\n\n‘You shall not commit adultery;’\n\nbut I tell you that everyone who gazes at a woman to lust after her has committed adultery with her already in his heart.\n\n\nIf your right eye causes you to stumble, pluck it out and throw it away from you. For it is more profitable for you that one of your members should perish, than for your whole body to be cast into Gehenna.\n\nIf your right hand causes you to stumble, cut it off, and throw it away from you. For it is more profitable for you that one of your members should perish, than for your whole body to be cast into Gehenna.\n\n“It was also said, ‘Whoever shall put away his wife, let him give her a writing of divorce,’\n\nbut I tell you that whoever puts away his wife, except for the cause of sexual immorality, makes her an adulteress; and whoever marries her when she is put away commits adultery.\n\n“Again you have heard that it was said to them of old time, ‘You shall not make false vows, but shall perform to the Lord your vows,’\n\nbut I tell you, don’t swear at all: neither by heaven, for it is the throne of God;\n\n\nnor by the earth, for it is the footstool of his feet; nor by Jerusalem, for it is the city of the great King.\n\n\nNeither shall you swear by your head, for you can’t make one hair white or black.\n\n\nBut let your ‘Yes’ be ‘Yes’ and your ‘No’ be ‘No.’ Whatever is more than these is of the evil one.\n\n“You have heard that it was said, ‘An eye for an eye, and a tooth for a tooth.’\n\nBut I tell you, don’t resist him who is evil; but whoever strikes you on your right cheek, turn to him the other also.\n\n\nIf anyone sues you to take away your coat, let him have your cloak also.\n\n\nWhoever compels you to go one mile, go with him two.\n\n\nGive to him who asks you, and don’t turn away him who desires to borrow from you.\n\n“You have heard that it was said, ‘You shall love your neighbor\n\nand hate your enemy.’\n\nBut I tell you, love your enemies, bless those who curse you, do good to those who hate you, and pray for those who mistreat you and persecute you,\n\n\nthat you may be children of your Father who is in heaven. For he makes his sun to rise on the evil and the good, and sends rain on the just and the unjust.\n\n\nFor if you love those who love you, what reward do you have? Don’t even the tax collectors do the same?\n\n\nIf you only greet your friends, what more do you do than others? Don’t even the tax collectors\ndo the same?\n\n\nTherefore you shall be perfect, just as your Father in heaven is perfect.\n",
  "translation_id": "web",
  "translation_name": "World English Bible",
  "translation_note": "Public Domain"
}